ballistics_engine/__init__.py
ballistics_engine/ballistics_engine.cpython-311-darwin.so
ballistics_engine-0.13.17.dist-info/METADATA
ballistics_engine-0.13.17.dist-info/WHEEL
ballistics_engine-0.13.17.dist-info/licenses/LICENSE
ballistics_engine-0.13.17.dist-info/licenses/LICENSE-APACHE
ballistics_engine-0.13.17.dist-info/RECORD
