Metadata-Version: 2.4
Name: ballistics-engine
Version: 0.13.17
Classifier: Programming Language :: Rust
Classifier: Programming Language :: Python :: Implementation :: CPython
Classifier: Programming Language :: Python :: Implementation :: PyPy
Classifier: Development Status :: 4 - Beta
Classifier: Intended Audience :: Science/Research
Classifier: License :: OSI Approved :: MIT License
Classifier: License :: OSI Approved :: Apache Software License
Classifier: Topic :: Scientific/Engineering :: Physics
License-File: LICENSE
License-File: LICENSE-APACHE
Summary: High-performance ballistics trajectory engine with professional physics
Keywords: ballistics,trajectory,physics,simulation
Author-email: Alex Jokela <email@tinycomputers.io>
License: MIT OR Apache-2.0
Requires-Python: >=3.8
Project-URL: Documentation, https://docs.rs/ballistics-engine
Project-URL: Homepage, https://ballistics.rs/
Project-URL: Repository, https://github.com/ajokela/ballistics-engine-py
